<?xml version="1.0" encoding="UTF-8"?>
<dbdesigner>
    <!--Program Flags-->
    <program>
        <file_purpose>simulation</file_purpose>
        <version>TBD</version>
        <date>2018-01-15 13:18:26</date>
    </program>
    <sim_params>
        <xml_path></xml_path>
    </sim_params>
    <!--GUI Flags-->
    <gui>
        <zoom>1</zoom>
        <scroll x="-119" y="-119"/>
    </gui>
    <!--Layer Properties-->
    <!--Layer ID is intrinsic to the layer order-->
    <layer_prop>
        <name>Lattice</name>
        <type>Lattice</type>
        <zheight>0</zheight>
        <visible>1</visible>
        <active>0</active>
    </layer_prop>
    <layer_prop>
        <name>Surface</name>
        <type>DB</type>
        <zheight>0</zheight>
        <visible>1</visible>
        <active>0</active>
    </layer_prop>
    <layer_prop>
        <name>Metal</name>
        <type>Electrode</type>
        <zheight>-1e-7</zheight>
        <visible>1</visible>
        <active>0</active>
    </layer_prop>
    <!--Item Hierarchy-->
    <design>
        <!--Lattice-->
        <layer type="Lattice"/>
        <!--Surface-->
        <layer type="DB"/>
        <!--Metal-->
        <layer type="Electrode">
            <electrode>
                <layer_id>2</layer_id>
                <dim x1="-6" y1="71" x2="199" y2="220"/>
                <potential>0</potential>
                <electrode_type>0</electrode_type>
            </electrode>
            <electrode>
                <layer_id>2</layer_id>
                <dim x1="259" y1="77" x2="463" y2="173"/>
                <potential>5</potential>
                <electrode_type>0</electrode_type>
            </electrode>
            <electrode>
                <layer_id>2</layer_id>
                <dim x1="483" y1="51" x2="684" y2="178"/>
                <potential>10</potential>
                <electrode_type>0</electrode_type>
            </electrode>
        </layer>
    </design>
</dbdesigner>